README.rst
setup.py
aci/VarScan.v2.3.9.jar
aci/__init__.py
aci/aci
aci/example.input.tab
aci.egg-info/PKG-INFO
aci.egg-info/SOURCES.txt
aci.egg-info/dependency_links.txt
aci.egg-info/top_level.txt