Metadata-Version: 1.1
Name: aci
Version: 1.3
Summary: Analyzer of CRISPR Indel
Home-page: www.calyx.biz
Author: Yingxiang Li
Author-email: xlccalyx@gmail.com
License: GPLv3
Download-URL: http://www.calyx.biz/downloading--1997936733.html
Keywords: Analyzer CRISPR Indel
Platform: UNKNOWN
Classifier: Development Status :: 3 - Alpha
Classifier: Intended Audience :: Developers
Classifier: Topic :: Software Development :: Build Tools
Classifier: License :: OSI Approved :: GNU General Public License v3 (GPLv3)
Classifier: Programming Language :: Python :: 2.7
